uset/.DS_Store
uset/__init__.py
uset-0.1.0.dist-info/WHEEL
uset-0.1.0.dist-info/METADATA
uset-0.1.0.dist-info/RECORD
