Metadata-Version: 2.1
Name: uset
Version: 0.1.0
Summary: 
Author: Josh Orr
Author-email: josh@orr.blue
Requires-Python: >=3.8,<4.0
Classifier: Programming Language :: Python :: 3
Classifier: Programming Language :: Python :: 3.8
Classifier: Programming Language :: Python :: 3.9
Classifier: Programming Language :: Python :: 3.10
